[
  {
    "symbol": "CRM",
    "strategy_name": "trend_filtered_mean_reversion",
    "parameters": {
      "z_window": 51,
      "z_threshold": 2.25,
      "trend_window": 350
    },
    "frozen_at": "2026-07-06T16:26:19.227397Z",
    "score": {
      "forward_bars": 4,
      "forward_return": 0.0,
      "forward_sharpe": 0.0,
      "buy_and_hold_return": -0.014065723419223408,
      "buy_and_hold_sharpe": -2.4433665759316106,
      "beats_buy_and_hold": true,
      "as_of": "2026-07-10T04:00:00Z",
      "forward_equity": [
        {
          "timestamp": "2026-07-07T04:00:00Z",
          "strategy_equity": 1.0,
          "buy_and_hold_equity": 1.0233625725335072
        },
        {
          "timestamp": "2026-07-08T04:00:00Z",
          "strategy_equity": 1.0,
          "buy_and_hold_equity": 1.0056142954040796
        },
        {
          "timestamp": "2026-07-09T04:00:00Z",
          "strategy_equity": 1.0,
          "buy_and_hold_equity": 0.9809840379469015
        },
        {
          "timestamp": "2026-07-10T04:00:00Z",
          "strategy_equity": 1.0,
          "buy_and_hold_equity": 0.9859342765807766
        }
      ]
    },
    "status": "open",
    "closed_at": null,
    "exit_reasons": []
  },
  {
    "symbol": "LOW",
    "strategy_name": "rsi_mean_reversion",
    "parameters": {
      "window": 64,
      "oversold": 42.875,
      "overbought": 74.25
    },
    "frozen_at": "2026-07-06T16:26:19.227397Z",
    "score": {
      "forward_bars": 4,
      "forward_return": -0.0010000000000000009,
      "forward_sharpe": -7.937253933193772,
      "buy_and_hold_return": -0.05429436971263901,
      "buy_and_hold_sharpe": -13.562154540871472,
      "beats_buy_and_hold": true,
      "as_of": "2026-07-10T04:00:00Z",
      "forward_equity": [
        {
          "timestamp": "2026-07-07T04:00:00Z",
          "strategy_equity": 1.0,
          "buy_and_hold_equity": 0.9871301947767012
        },
        {
          "timestamp": "2026-07-08T04:00:00Z",
          "strategy_equity": 1.0,
          "buy_and_hold_equity": 0.9511574177815597
        },
        {
          "timestamp": "2026-07-09T04:00:00Z",
          "strategy_equity": 1.0,
          "buy_and_hold_equity": 0.9518276921611748
        },
        {
          "timestamp": "2026-07-10T04:00:00Z",
          "strategy_equity": 0.999,
          "buy_and_hold_equity": 0.945705630287361
        }
      ]
    },
    "status": "open",
    "closed_at": null,
    "exit_reasons": []
  },
  {
    "symbol": "ACN",
    "strategy_name": "bollinger_bands",
    "parameters": {
      "window": 200,
      "num_std": 2.75
    },
    "frozen_at": "2026-07-12T09:05:59.020701Z",
    "score": {
      "forward_bars": 0,
      "forward_return": 0.0,
      "forward_sharpe": 0.0,
      "buy_and_hold_return": 0.0,
      "buy_and_hold_sharpe": 0.0,
      "beats_buy_and_hold": false,
      "as_of": "2026-07-10T04:00:00Z",
      "forward_equity": []
    },
    "status": "open",
    "closed_at": null,
    "exit_reasons": []
  },
  {
    "symbol": "ANET",
    "strategy_name": "trend_filtered_mean_reversion",
    "parameters": {
      "z_window": 38,
      "z_threshold": 0.625,
      "trend_window": 400
    },
    "frozen_at": "2026-07-12T09:05:59.020701Z",
    "score": {
      "forward_bars": 0,
      "forward_return": 0.0,
      "forward_sharpe": 0.0,
      "buy_and_hold_return": 0.0,
      "buy_and_hold_sharpe": 0.0,
      "beats_buy_and_hold": false,
      "as_of": "2026-07-10T04:00:00Z",
      "forward_equity": []
    },
    "status": "open",
    "closed_at": null,
    "exit_reasons": []
  },
  {
    "symbol": "APA",
    "strategy_name": "trend_filtered_mean_reversion",
    "parameters": {
      "z_window": 64,
      "z_threshold": 2.25,
      "trend_window": 300
    },
    "frozen_at": "2026-07-12T09:05:59.020701Z",
    "score": {
      "forward_bars": 0,
      "forward_return": 0.0,
      "forward_sharpe": 0.0,
      "buy_and_hold_return": 0.0,
      "buy_and_hold_sharpe": 0.0,
      "beats_buy_and_hold": false,
      "as_of": "2026-07-10T04:00:00Z",
      "forward_equity": []
    },
    "status": "open",
    "closed_at": null,
    "exit_reasons": []
  },
  {
    "symbol": "BBY",
    "strategy_name": "rsi_mean_reversion",
    "parameters": {
      "window": 100,
      "oversold": 42.875,
      "overbought": 75.0
    },
    "frozen_at": "2026-07-12T09:05:59.020701Z",
    "score": {
      "forward_bars": 0,
      "forward_return": 0.0,
      "forward_sharpe": 0.0,
      "buy_and_hold_return": 0.0,
      "buy_and_hold_sharpe": 0.0,
      "beats_buy_and_hold": false,
      "as_of": "2026-07-10T04:00:00Z",
      "forward_equity": []
    },
    "status": "open",
    "closed_at": null,
    "exit_reasons": []
  },
  {
    "symbol": "BIIB",
    "strategy_name": "rsi_mean_reversion",
    "parameters": {
      "window": 100,
      "oversold": 49.0,
      "overbought": 75.0
    },
    "frozen_at": "2026-07-12T09:05:59.020701Z",
    "score": {
      "forward_bars": 0,
      "forward_return": 0.0,
      "forward_sharpe": 0.0,
      "buy_and_hold_return": 0.0,
      "buy_and_hold_sharpe": 0.0,
      "beats_buy_and_hold": false,
      "as_of": "2026-07-10T04:00:00Z",
      "forward_equity": []
    },
    "status": "open",
    "closed_at": null,
    "exit_reasons": []
  },
  {
    "symbol": "CASY",
    "strategy_name": "rsi_mean_reversion",
    "parameters": {
      "window": 51,
      "oversold": 49.0,
      "overbought": 75.0
    },
    "frozen_at": "2026-07-12T09:05:59.020701Z",
    "score": {
      "forward_bars": 0,
      "forward_return": 0.0,
      "forward_sharpe": 0.0,
      "buy_and_hold_return": 0.0,
      "buy_and_hold_sharpe": 0.0,
      "beats_buy_and_hold": false,
      "as_of": "2026-07-10T04:00:00Z",
      "forward_equity": []
    },
    "status": "open",
    "closed_at": null,
    "exit_reasons": []
  },
  {
    "symbol": "CLX",
    "strategy_name": "rsi_mean_reversion",
    "parameters": {
      "window": 51,
      "oversold": 49.0,
      "overbought": 86.625
    },
    "frozen_at": "2026-07-12T09:05:59.020701Z",
    "score": {
      "forward_bars": 0,
      "forward_return": 0.0,
      "forward_sharpe": 0.0,
      "buy_and_hold_return": 0.0,
      "buy_and_hold_sharpe": 0.0,
      "beats_buy_and_hold": false,
      "as_of": "2026-07-10T04:00:00Z",
      "forward_equity": []
    },
    "status": "open",
    "closed_at": null,
    "exit_reasons": []
  },
  {
    "symbol": "DLR",
    "strategy_name": "bollinger_bands",
    "parameters": {
      "window": 150,
      "num_std": 2.0625
    },
    "frozen_at": "2026-07-12T09:05:59.020701Z",
    "score": {
      "forward_bars": 0,
      "forward_return": 0.0,
      "forward_sharpe": 0.0,
      "buy_and_hold_return": 0.0,
      "buy_and_hold_sharpe": 0.0,
      "beats_buy_and_hold": false,
      "as_of": "2026-07-10T04:00:00Z",
      "forward_equity": []
    },
    "status": "open",
    "closed_at": null,
    "exit_reasons": []
  },
  {
    "symbol": "DVA",
    "strategy_name": "rsi_mean_reversion",
    "parameters": {
      "window": 88,
      "oversold": 42.875,
      "overbought": 75.0
    },
    "frozen_at": "2026-07-12T09:05:59.020701Z",
    "score": {
      "forward_bars": 0,
      "forward_return": 0.0,
      "forward_sharpe": 0.0,
      "buy_and_hold_return": 0.0,
      "buy_and_hold_sharpe": 0.0,
      "beats_buy_and_hold": false,
      "as_of": "2026-07-10T04:00:00Z",
      "forward_equity": []
    },
    "status": "open",
    "closed_at": null,
    "exit_reasons": []
  },
  {
    "symbol": "ECL",
    "strategy_name": "bollinger_bands",
    "parameters": {
      "window": 76,
      "num_std": 2.0625
    },
    "frozen_at": "2026-07-12T09:05:59.020701Z",
    "score": {
      "forward_bars": 0,
      "forward_return": 0.0,
      "forward_sharpe": 0.0,
      "buy_and_hold_return": 0.0,
      "buy_and_hold_sharpe": 0.0,
      "beats_buy_and_hold": false,
      "as_of": "2026-07-10T04:00:00Z",
      "forward_equity": []
    },
    "status": "open",
    "closed_at": null,
    "exit_reasons": []
  },
  {
    "symbol": "FAST",
    "strategy_name": "rsi_mean_reversion",
    "parameters": {
      "window": 51,
      "oversold": 49.0,
      "overbought": 75.0
    },
    "frozen_at": "2026-07-12T09:05:59.020701Z",
    "score": {
      "forward_bars": 0,
      "forward_return": 0.0,
      "forward_sharpe": 0.0,
      "buy_and_hold_return": 0.0,
      "buy_and_hold_sharpe": 0.0,
      "beats_buy_and_hold": false,
      "as_of": "2026-07-10T04:00:00Z",
      "forward_equity": []
    },
    "status": "open",
    "closed_at": null,
    "exit_reasons": []
  },
  {
    "symbol": "FIS",
    "strategy_name": "trend_filtered_mean_reversion",
    "parameters": {
      "z_window": 51,
      "z_threshold": 2.25,
      "trend_window": 400
    },
    "frozen_at": "2026-07-12T09:05:59.020701Z",
    "score": {
      "forward_bars": 0,
      "forward_return": 0.0,
      "forward_sharpe": 0.0,
      "buy_and_hold_return": 0.0,
      "buy_and_hold_sharpe": 0.0,
      "beats_buy_and_hold": false,
      "as_of": "2026-07-10T04:00:00Z",
      "forward_equity": []
    },
    "status": "open",
    "closed_at": null,
    "exit_reasons": []
  },
  {
    "symbol": "IT",
    "strategy_name": "trend_filtered_mean_reversion",
    "parameters": {
      "z_window": 38,
      "z_threshold": 1.6875,
      "trend_window": 300
    },
    "frozen_at": "2026-07-12T09:05:59.020701Z",
    "score": {
      "forward_bars": 0,
      "forward_return": 0.0,
      "forward_sharpe": 0.0,
      "buy_and_hold_return": 0.0,
      "buy_and_hold_sharpe": 0.0,
      "beats_buy_and_hold": false,
      "as_of": "2026-07-10T04:00:00Z",
      "forward_equity": []
    },
    "status": "open",
    "closed_at": null,
    "exit_reasons": []
  },
  {
    "symbol": "NOW",
    "strategy_name": "sma",
    "parameters": {
      "fast": 75,
      "slow": 251
    },
    "frozen_at": "2026-07-12T09:05:59.020701Z",
    "score": {
      "forward_bars": 0,
      "forward_return": 0.0,
      "forward_sharpe": 0.0,
      "buy_and_hold_return": 0.0,
      "buy_and_hold_sharpe": 0.0,
      "beats_buy_and_hold": false,
      "as_of": "2026-07-10T04:00:00Z",
      "forward_equity": []
    },
    "status": "open",
    "closed_at": null,
    "exit_reasons": []
  },
  {
    "symbol": "NSC",
    "strategy_name": "trend_filtered_mean_reversion",
    "parameters": {
      "z_window": 38,
      "z_threshold": 2.8125,
      "trend_window": 262
    },
    "frozen_at": "2026-07-12T09:05:59.020701Z",
    "score": {
      "forward_bars": 0,
      "forward_return": 0.0,
      "forward_sharpe": 0.0,
      "buy_and_hold_return": 0.0,
      "buy_and_hold_sharpe": 0.0,
      "beats_buy_and_hold": false,
      "as_of": "2026-07-10T04:00:00Z",
      "forward_equity": []
    },
    "status": "open",
    "closed_at": null,
    "exit_reasons": []
  },
  {
    "symbol": "ODFL",
    "strategy_name": "rsi_mean_reversion",
    "parameters": {
      "window": 51,
      "oversold": 49.0,
      "overbought": 75.0
    },
    "frozen_at": "2026-07-12T09:05:59.020701Z",
    "score": {
      "forward_bars": 0,
      "forward_return": 0.0,
      "forward_sharpe": 0.0,
      "buy_and_hold_return": 0.0,
      "buy_and_hold_sharpe": 0.0,
      "beats_buy_and_hold": false,
      "as_of": "2026-07-10T04:00:00Z",
      "forward_equity": []
    },
    "status": "open",
    "closed_at": null,
    "exit_reasons": []
  },
  {
    "symbol": "VRT",
    "strategy_name": "triple_ma_alignment",
    "parameters": {
      "fast": 1,
      "medium": 126,
      "slow": 152
    },
    "frozen_at": "2026-07-12T09:05:59.020701Z",
    "score": {
      "forward_bars": 0,
      "forward_return": 0.0,
      "forward_sharpe": 0.0,
      "buy_and_hold_return": 0.0,
      "buy_and_hold_sharpe": 0.0,
      "beats_buy_and_hold": false,
      "as_of": "2026-07-10T04:00:00Z",
      "forward_equity": []
    },
    "status": "open",
    "closed_at": null,
    "exit_reasons": []
  }
]
